{"captions":[{"duration":2421,"content":"Il 5 novembre 1990,","startOfParagraph":true,"startTime":1912},{"duration":2799,"content":"un uomo di nome El-Sayyid Nosair entrò","startOfParagraph":false,"startTime":4333},{"duration":2385,"content":"in un albergo a Manhattan","startOfParagraph":false,"startTime":7132},{"duration":2965,"content":"e assassinò il Rabbino Meir Kahane,","startOfParagraph":false,"startTime":9517},{"duration":3798,"content":"il leader della Lega di Difesa Ebraica.","startOfParagraph":false,"startTime":12482},{"duration":2660,"content":"Nosair fu inizialmente dichiarato \nnon colpevole,","startOfParagraph":false,"startTime":16280},{"duration":3626,"content":"ma mentre scontava una pena \nper accuse minori,","startOfParagraph":false,"startTime":18940},{"duration":2594,"content":"cominciò a pianificare attacchi, \ninsieme ad altri uomini,","startOfParagraph":false,"startTime":22566},{"duration":1891,"content":"a una dozzina di punti \nnevralgici di New York,","startOfParagraph":false,"startTime":25160},{"duration":2344,"content":"compresi tunnel, sinagoghe","startOfParagraph":false,"startTime":27051},{"duration":2886,"content":"e la sede centrale delle Nazioni Unite.","startOfParagraph":false,"startTime":29395},{"duration":1723,"content":"Per fortuna, quei piani furono sventati","startOfParagraph":false,"startTime":32281},{"duration":2837,"content":"da un informatore dell'FBI.","startOfParagraph":false,"startTime":34004},{"duration":2556,"content":"Sfortunatamente, non fu così \nper l'attentato","startOfParagraph":false,"startTime":36841},{"duration":3181,"content":"al World Trade Center del 1993.","startOfParagraph":false,"startTime":39397},{"duration":1739,"content":"Nosair venne condannato","startOfParagraph":false,"startTime":42578},{"duration":3424,"content":"per il suo coinvolgimento nel complotto.","startOfParagraph":false,"startTime":44317},{"duration":4247,"content":"El-Sayyid Nosair è mio padre.","startOfParagraph":false,"startTime":47741},{"duration":1910,"content":"Sono nato a Pittsburgh, Pennsylvania,","startOfParagraph":false,"startTime":51988},{"duration":3724,"content":"nel 1983, da mio padre, \nun ingegnere egiziano,","startOfParagraph":false,"startTime":53898},{"duration":3195,"content":"e una madre americana amorevole, \ninsegnante di scuola elementare,","startOfParagraph":false,"startTime":57622},{"duration":1251,"content":"che insieme cercarono in tutti i modi","startOfParagraph":false,"startTime":60817},{"duration":3113,"content":"di darmi un'infanzia felice.","startOfParagraph":false,"startTime":62068},{"duration":1542,"content":"Fu solo all'età di sette anni","startOfParagraph":false,"startTime":65181},{"duration":3543,"content":"che nella nostra famiglia \nle dinamiche iniziarono a cambiare.","startOfParagraph":false,"startTime":66723},{"duration":3150,"content":"Mio padre mi fece conoscere \nun lato dell'Islam","startOfParagraph":false,"startTime":70266},{"duration":2927,"content":"che poche persone, compresa \nla maggioranza dei Musulmani,","startOfParagraph":false,"startTime":73416},{"duration":2717,"content":"riescono a vedere.","startOfParagraph":false,"startTime":76343},{"duration":1669,"content":"So per esperienza \nche quando le persone","startOfParagraph":false,"startTime":79060},{"duration":2362,"content":"prendono il tempo \ndi interagire le une con le altre,","startOfParagraph":false,"startTime":80729},{"duration":3058,"content":"in breve si rendono conto \nche, perlopiù,","startOfParagraph":false,"startTime":83091},{"duration":2452,"content":"nella vita cerchiamo tutti \nle stesse cose.","startOfParagraph":false,"startTime":86149},{"duration":3177,"content":"Tuttavia in ogni religione, \nin ogni popolazione,","startOfParagraph":false,"startTime":88601},{"duration":2588,"content":"potrete trovare una piccola \npercentuale di persone","startOfParagraph":false,"startTime":91778},{"duration":2958,"content":"così fervidamente attaccate \nalle proprie convinzioni","startOfParagraph":false,"startTime":94366},{"duration":2764,"content":"da sentirsi in dovere di usare \nqualunque mezzo necessario","startOfParagraph":false,"startTime":97324},{"duration":3596,"content":"per far vivere gli altri come loro.","startOfParagraph":false,"startTime":100088},{"duration":1861,"content":"Qualche mese prima del suo arresto,","startOfParagraph":false,"startTime":103684},{"duration":2002,"content":"mi fece sedere e mi spiegò","startOfParagraph":false,"startTime":105545},{"duration":3119,"content":"che, negli ultimi weekend, \nlui e alcuni amici","startOfParagraph":false,"startTime":107547},{"duration":2114,"content":"erano andati a un poligono di tiro \na Long Island,","startOfParagraph":false,"startTime":110666},{"duration":2183,"content":"per fare pratica.","startOfParagraph":false,"startTime":112780},{"duration":3690,"content":"Mi disse che sarei andato con lui \nla mattina successiva.","startOfParagraph":false,"startTime":114963},{"duration":1811,"content":"Arrivammo al poligono di tiro \ndi Calverton,","startOfParagraph":false,"startTime":118653},{"duration":2515,"content":"che all'insaputa del nostro gruppo \nera sorvegliato","startOfParagraph":false,"startTime":120464},{"duration":3121,"content":"dall'FBI.","startOfParagraph":false,"startTime":122979},{"duration":981,"content":"Quando fu il mio turno di sparare,","startOfParagraph":false,"startTime":126100},{"duration":2686,"content":"mio padre mi aiutò a tenere \nil fucile sulla spalla","startOfParagraph":false,"startTime":127081},{"duration":1445,"content":"e mi spiegò come puntare al bersaglio","startOfParagraph":false,"startTime":129767},{"duration":3141,"content":"a circa 28 metri di distanza.","startOfParagraph":false,"startTime":131212},{"duration":2343,"content":"Quel giorno, l'ultima pallottola \nche sparai","startOfParagraph":false,"startTime":134353},{"duration":3019,"content":"colpì la luce arancione \nin cima al bersaglio","startOfParagraph":false,"startTime":136696},{"duration":3129,"content":"e con sorpresa di tutti, \nma in particolare mia,","startOfParagraph":false,"startTime":139715},{"duration":3974,"content":"il bersaglio prese fuoco.","startOfParagraph":false,"startTime":142844},{"duration":1901,"content":"Mio zio si girò verso gli altri uomini,","startOfParagraph":false,"startTime":146818},{"duration":3321,"content":"e in arabo disse, \"ibn abuh\".","startOfParagraph":false,"startTime":148719},{"duration":3755,"content":"Tale padre, tale figlio.","startOfParagraph":false,"startTime":152040},{"duration":2607,"content":"Tutti sembravano ridere a crepapelle, \ndopo quel commento,","startOfParagraph":false,"startTime":155795},{"duration":1780,"content":"ma solo qualche anno dopo","startOfParagraph":false,"startTime":158402},{"duration":3775,"content":"compresi appieno \ncosa ritenessero divertente.","startOfParagraph":false,"startTime":160182},{"duration":2300,"content":"Pensavano di vedere in me \nla stessa distruttività","startOfParagraph":false,"startTime":163957},{"duration":3331,"content":"di cui era capace mio padre.","startOfParagraph":false,"startTime":166257},{"duration":2379,"content":"Quegli uomini furono poi condannati","startOfParagraph":false,"startTime":169588},{"duration":3973,"content":"per aver posizionato un furgone \ncon 700 kg di esplosivo","startOfParagraph":false,"startTime":171967},{"duration":4149,"content":"nel seminterrato di un parcheggio \ndel World Trade Center,","startOfParagraph":false,"startTime":175940},{"duration":2841,"content":"causando un'esplosione \nche uccise sei persone","startOfParagraph":false,"startTime":180089},{"duration":3380,"content":"e ne ferì altre 1000.","startOfParagraph":false,"startTime":182930},{"duration":2391,"content":"Era questo il genere di persone \nche avevo di fronte.","startOfParagraph":false,"startTime":186310},{"duration":4196,"content":"Era questo il genere di persone \nche chiamavo \"ammu\", zio.","startOfParagraph":false,"startTime":188701},{"duration":1771,"content":"All'età di 19 anni,","startOfParagraph":false,"startTime":192897},{"duration":3269,"content":"mi ero già trasferito \n20 volte in vita mia,","startOfParagraph":false,"startTime":194668},{"duration":2029,"content":"e quella instabilità, \ndurante la mia infanzia,","startOfParagraph":false,"startTime":197937},{"duration":1474,"content":"mi precluse l'opportunità","startOfParagraph":false,"startTime":199966},{"duration":1881,"content":"di farmi dei veri amici.","startOfParagraph":false,"startTime":201440},{"duration":3153,"content":"Ogni volta che iniziavo a sentirmi \na mio agio con qualcuno,","startOfParagraph":false,"startTime":203321},{"duration":3169,"content":"era il momento \ndi fare le valigie e trasferirsi.","startOfParagraph":false,"startTime":206474},{"duration":2179,"content":"Essendo l'eterna \"faccia nuova\" \ndella classe,","startOfParagraph":false,"startTime":209643},{"duration":2639,"content":"ero spesso preso di mira dai bulli.","startOfParagraph":false,"startTime":211822},{"duration":2310,"content":"Tenevo segreta la mia identità \ndai miei compagni","startOfParagraph":false,"startTime":214461},{"duration":1318,"content":"per evitare di essere preso di mira,","startOfParagraph":false,"startTime":216771},{"duration":3396,"content":"ma a quanto pare, essere il nuovo \npacioccone della classe","startOfParagraph":false,"startTime":218089},{"duration":2517,"content":"era già un argomento sufficiente.","startOfParagraph":false,"startTime":221485},{"duration":2197,"content":"Quindi passavo il tempo \nperlopiù a casa,","startOfParagraph":false,"startTime":224002},{"duration":1671,"content":"a leggere libri, guardare la TV","startOfParagraph":false,"startTime":226199},{"duration":1769,"content":"o giocare ai videogiochi.","startOfParagraph":false,"startTime":227870},{"duration":2870,"content":"Ero quindi socialmente carente,","startOfParagraph":false,"startTime":229639},{"duration":2250,"content":"per usare un eufemismo;","startOfParagraph":false,"startTime":232509},{"duration":1435,"content":"e crescendo in un ambiente \ncosì intollerante,","startOfParagraph":false,"startTime":234759},{"duration":2480,"content":"non ero pronto al mondo reale.","startOfParagraph":false,"startTime":236194},{"duration":1719,"content":"Sono stato educato \na giudicare le persone","startOfParagraph":false,"startTime":238674},{"duration":2067,"content":"sulla base di parametri arbitrari,","startOfParagraph":false,"startTime":240393},{"duration":3743,"content":"come la razza o la religione.","startOfParagraph":false,"startTime":242460},{"duration":3151,"content":"Cosa mi ha aperto gli occhi, allora?","startOfParagraph":false,"startTime":246203},{"duration":1594,"content":"Una delle prime esperienze","startOfParagraph":false,"startTime":249354},{"duration":2182,"content":"che ha sfidato il mio modo di pensare","startOfParagraph":false,"startTime":250948},{"duration":2987,"content":"l'ho vissuta durante \nle elezioni presidenziali del 2000.","startOfParagraph":false,"startTime":253130},{"duration":2034,"content":"Attraverso un programma \ndi preparazione universitario,","startOfParagraph":false,"startTime":256117},{"duration":1134,"content":"ho potuto prendere parte","startOfParagraph":false,"startTime":258151},{"duration":3370,"content":"al Raduno Nazionale \ndella Gioventù di Philadelphia.","startOfParagraph":false,"startTime":259285},{"duration":2931,"content":"Il focus del mio gruppo era \nsulla violenza dei giovani,","startOfParagraph":false,"startTime":262655},{"duration":2351,"content":"ed essendo stato vittima di bullismo \nper gran parte della mia vita,","startOfParagraph":false,"startTime":265586},{"duration":4072,"content":"mi appassionai \nparticolarmente all'argomento.","startOfParagraph":false,"startTime":267937},{"duration":4313,"content":"I membri del nostro gruppo \nvenivano da percorsi di vita diversi.","startOfParagraph":false,"startTime":272009},{"duration":2008,"content":"Un giorno, verso \nla fine della convention,","startOfParagraph":false,"startTime":276322},{"duration":3088,"content":"scoprii che uno dei ragazzi \ncon cui avevo fatto amicizia","startOfParagraph":false,"startTime":278330},{"duration":2222,"content":"era Ebreo.","startOfParagraph":false,"startTime":281418},{"duration":1321,"content":"Ci erano voluti diversi giorni","startOfParagraph":false,"startTime":283640},{"duration":1643,"content":"perché quel dettaglio \nvenisse alla luce,","startOfParagraph":false,"startTime":284961},{"duration":3760,"content":"e mi resi conto non c'era \nnessuna naturale ostilità","startOfParagraph":false,"startTime":286604},{"duration":2245,"content":"tra noi due.","startOfParagraph":false,"startTime":290364},{"duration":3056,"content":"Non avevo mai avuto un amico ebreo,","startOfParagraph":false,"startTime":292609},{"duration":2809,"content":"e francamente mi sentivo orgoglioso","startOfParagraph":false,"startTime":295665},{"duration":1985,"content":"di essere riuscito\na superare una barriera","startOfParagraph":false,"startTime":298474},{"duration":2284,"content":"che per gran parte della vita \nmi avevano portato a credere","startOfParagraph":false,"startTime":300459},{"duration":2441,"content":"insormontabile.","startOfParagraph":false,"startTime":302743},{"duration":2016,"content":"Un altro punto di svolta fu quando","startOfParagraph":false,"startTime":305184},{"duration":2522,"content":"trovai un lavoro estivo \nai Busch Gardens,","startOfParagraph":false,"startTime":307200},{"duration":2392,"content":"un parco di divertimenti.","startOfParagraph":false,"startTime":309722},{"duration":2896,"content":"Lì entrai in contatto con persone \ndi ogni religione e cultura,","startOfParagraph":false,"startTime":312114},{"duration":2357,"content":"e quell'esperienza \nsi rivelò fondamentale","startOfParagraph":false,"startTime":315010},{"duration":3881,"content":"nello sviluppo del mio carattere.","startOfParagraph":false,"startTime":317367},{"duration":1260,"content":"Per gran parte della vita, \nmi è stato insegnato","startOfParagraph":false,"startTime":321248},{"duration":3746,"content":"che l'omosessualità era un peccato, \ne che, di conseguenza,","startOfParagraph":false,"startTime":322508},{"duration":3465,"content":"tutti i gay costituivano \nun'influenza negativa.","startOfParagraph":false,"startTime":326254},{"duration":2261,"content":"Ma guarda caso, ebbi l'opportunità","startOfParagraph":false,"startTime":329719},{"duration":1766,"content":"di lavorare con artisti gay","startOfParagraph":false,"startTime":331980},{"duration":1380,"content":"a uno spettacolo,","startOfParagraph":false,"startTime":333746},{"duration":2534,"content":"e presto scoprii che molti di loro \nerano tra le persone più buone,","startOfParagraph":false,"startTime":335126},{"duration":3889,"content":"e meno critiche \nche avevo mai conosciuto.","startOfParagraph":false,"startTime":337660},{"duration":2243,"content":"Essere vittima di bullismo da ragazzo","startOfParagraph":false,"startTime":341549},{"duration":2288,"content":"ha creato in me un senso di empatia","startOfParagraph":false,"startTime":343792},{"duration":1546,"content":"verso la sofferenza \ndegli altri,","startOfParagraph":false,"startTime":346080},{"duration":1948,"content":"e ora non mi viene affatto naturale","startOfParagraph":false,"startTime":347626},{"duration":1968,"content":"trattare le persone buone","startOfParagraph":false,"startTime":349574},{"duration":4028,"content":"in modo diverso da come \nvorrei essere trattato io.","startOfParagraph":false,"startTime":351542},{"duration":1935,"content":"A causa di quel sentimento, \nsono stato in grado","startOfParagraph":false,"startTime":355570},{"duration":4387,"content":"di contrastare gli stereotipi \ninculcatimi da bambino","startOfParagraph":false,"startTime":357505},{"duration":3363,"content":"con esperienze di vita vera \ne interazioni.","startOfParagraph":false,"startTime":361892},{"duration":2342,"content":"Non so cosa voglia dire essere gay,","startOfParagraph":false,"startTime":365255},{"duration":1663,"content":"ma so bene cosa significhi \nessere giudicato","startOfParagraph":false,"startTime":367597},{"duration":3976,"content":"per qualcosa che è al di fuori \ndel mio controllo.","startOfParagraph":false,"startTime":369260},{"duration":3735,"content":"Poi c'è stato il \"Daily Show\".","startOfParagraph":false,"startTime":373236},{"duration":2272,"content":"Ogni notte, Jon Stewart mi costringeva","startOfParagraph":false,"startTime":376971},{"duration":3679,"content":"a essere intellettualmente onesto \ncon me stesso sulla mia intolleranza","startOfParagraph":false,"startTime":379243},{"duration":2317,"content":"e mi aiutò a rendermi conto \nche la razza di una persona,","startOfParagraph":false,"startTime":382922},{"duration":3096,"content":"la religione o l'orientamento sessuale","startOfParagraph":false,"startTime":385239},{"duration":4643,"content":"non avevano niente a che fare \ncon le qualità del loro carattere.","startOfParagraph":false,"startTime":388335},{"duration":3375,"content":"In un certo senso è stato \nun padre per me,","startOfParagraph":false,"startTime":392978},{"duration":3341,"content":"quando ne cercavo disperatamente uno.","startOfParagraph":false,"startTime":396353},{"duration":3904,"content":"L'ispirazione può spesso \narrivare da posti inaspettati,","startOfParagraph":false,"startTime":399694},{"duration":2385,"content":"e il fatto che un comico ebreo \navesse fatto di più,","startOfParagraph":false,"startTime":403598},{"duration":2340,"content":"per influenzare positivamente \nla visione del mondo,","startOfParagraph":false,"startTime":405983},{"duration":1847,"content":"di un estremista come mio padre","startOfParagraph":false,"startTime":408323},{"duration":3383,"content":"mi è rimasto dentro.","startOfParagraph":false,"startTime":410170},{"duration":2160,"content":"Un giorno, ho fatto \nuna chiacchierata con mia madre","startOfParagraph":false,"startTime":413553},{"duration":2170,"content":"su come la mia visione del mondo \nstesse cambiando,","startOfParagraph":false,"startTime":415713},{"duration":2676,"content":"e lei mi disse una cosa","startOfParagraph":false,"startTime":417883},{"duration":1531,"content":"che porterò nel cuore","startOfParagraph":false,"startTime":420559},{"duration":3249,"content":"tutta la vita.","startOfParagraph":false,"startTime":422090},{"duration":1471,"content":"Mi guardò con gli occhi stanchi","startOfParagraph":false,"startTime":425339},{"duration":1722,"content":"di chi ha provato","startOfParagraph":false,"startTime":426810},{"duration":4058,"content":"dogmatismo da bastare \nper una vita intera, e mi disse,","startOfParagraph":false,"startTime":428532},{"duration":3673,"content":"\"Sono stanca di odiare le persone.\"","startOfParagraph":false,"startTime":432590},{"duration":2877,"content":"In quel momento, mi sono reso conto \ndi quanta energia negativa","startOfParagraph":false,"startTime":436263},{"duration":3416,"content":"richieda tutto quell'odio.","startOfParagraph":false,"startTime":439140},{"duration":2901,"content":"Zak Ebrahim non è il mio vero nome.","startOfParagraph":false,"startTime":443979},{"duration":2035,"content":"L'ho cambiato quando \nla mia famiglia ha deciso","startOfParagraph":false,"startTime":446880},{"duration":1665,"content":"di tagliare i ponti con mio padre","startOfParagraph":false,"startTime":448915},{"duration":2362,"content":"e cominciare una nuova vita.","startOfParagraph":false,"startTime":450580},{"duration":2158,"content":"Perché, allora, \ndovrei uscire allo scoperto","startOfParagraph":false,"startTime":452942},{"duration":3400,"content":"e mettermi potenzialmente in pericolo?","startOfParagraph":false,"startTime":455100},{"duration":1868,"content":"Be', è semplice.","startOfParagraph":false,"startTime":458500},{"duration":3762,"content":"Lo faccio nella speranza \nche forse qualcuno, un giorno,","startOfParagraph":false,"startTime":460368},{"duration":2213,"content":"costretto a usare la violenza,","startOfParagraph":false,"startTime":464130},{"duration":2361,"content":"possa sentire la mia storia \ne rendersi conto","startOfParagraph":false,"startTime":466343},{"duration":2497,"content":"che c'è un modo migliore.","startOfParagraph":false,"startTime":468704},{"duration":1474,"content":"Che malgrado io sia stato sottoposto","startOfParagraph":false,"startTime":471201},{"duration":2756,"content":"a questa ideologia \nviolenta, intollerante,","startOfParagraph":false,"startTime":472675},{"duration":2489,"content":"non sono diventato fanatico.","startOfParagraph":false,"startTime":475431},{"duration":2637,"content":"Ho scelto invece di usare \nla mia esperienza","startOfParagraph":false,"startTime":477920},{"duration":2373,"content":"per contrastare il terrorismo,","startOfParagraph":false,"startTime":480557},{"duration":4391,"content":"l'intolleranza.","startOfParagraph":false,"startTime":482930},{"duration":2788,"content":"Lo faccio per le vittime del terrorismo","startOfParagraph":false,"startTime":487321},{"duration":2182,"content":"e per i loro cari,","startOfParagraph":false,"startTime":490109},{"duration":1833,"content":"per il terribile dolore e le perdite","startOfParagraph":false,"startTime":492291},{"duration":3201,"content":"che il terrorismo ha imposto loro.","startOfParagraph":false,"startTime":494124},{"duration":2368,"content":"Per le vittime del terrorismo, \nparlerò apertamente","startOfParagraph":false,"startTime":497325},{"duration":2532,"content":"contro questi atti insensati","startOfParagraph":false,"startTime":499693},{"duration":3994,"content":"e condannerò le azioni di mio padre.","startOfParagraph":false,"startTime":502225},{"duration":2643,"content":"Con quel semplice fatto, \nsono qui a prova del fatto","startOfParagraph":false,"startTime":506219},{"duration":4658,"content":"che la violenza non è intrinseca \nalla religione o alla razza,","startOfParagraph":false,"startTime":508862},{"duration":2913,"content":"e il figlio non è tenuto a seguire","startOfParagraph":false,"startTime":513520},{"duration":3082,"content":"le orme del padre.","startOfParagraph":false,"startTime":516433},{"duration":2789,"content":"Io non sono mio padre.","startOfParagraph":false,"startTime":519515},{"duration":2901,"content":"Grazie. \n(Applausi)","startOfParagraph":false,"startTime":522304},{"duration":3659,"content":"Grazie a tutti. \n(Applausi)","startOfParagraph":false,"startTime":525205},{"duration":2640,"content":"Grazie a tutti. \n(Applausi)","startOfParagraph":false,"startTime":528864},{"duration":4000,"content":"Grazie infinite. \n(Applausi)","startOfParagraph":false,"startTime":531504}]}